db_adapter/__init__.py
db_adapter/apps.py
db_adapter/models.py
db_adapter/name_builders.py
db_adapter/settings.py
db_adapter/utils.py
db_adapter/db/__init__.py
db_adapter/db/backends/__init__.py
db_adapter/db/backends/base/__init__.py
db_adapter/db/backends/base/operations.py
db_adapter/db/backends/base/schema.py
db_adapter/db/backends/oracle/__init__.py
db_adapter/db/backends/oracle/base.py
db_adapter/db/backends/oracle/constants.py
db_adapter/db/backends/oracle/operations.py
db_adapter/db/backends/oracle/schema.py
django_db_adapter-2.0.1.dist-info/LICENSE
django_db_adapter-2.0.1.dist-info/METADATA
django_db_adapter-2.0.1.dist-info/WHEEL
django_db_adapter-2.0.1.dist-info/top_level.txt
django_db_adapter-2.0.1.dist-info/RECORD
