Metadata-Version: 2.1
Name: django-db-adapter
Version: 2.0.1
Summary: A flexible toolkit for customize how Django creates the databse objects for the application schema
Home-page: https://github.com/weynelucas/django-db-adapter/
Author: Lucas Weyne
Author-email: weynelucas@gmail.com
License: UNKNOWN
Download-URL: https://github.com/weynelucas/django-db-adapter/archive/2.0.1.tar.gz
Keywords: django database schema editor oracle django-db-adapter
Platform: UNKNOWN
Classifier: Development Status :: 5 - Production/Stable
Classifier: Environment :: Web Environment
Classifier: Framework :: Django
Classifier: Framework :: Django :: 1.11
Classifier: Framework :: Django :: 2.2
Classifier: Intended Audience :: Developers
Classifier: License :: OSI Approved :: MIT License
Classifier: Operating System :: OS Independent
Classifier: Programming Language :: Python :: 3
Classifier: Programming Language :: Python :: 3.6
Classifier: Programming Language :: Python :: 3.7
Classifier: Programming Language :: Python :: 3.8
Classifier: Programming Language :: Python :: 3.9
Classifier: Topic :: Internet :: WWW/HTTP
Requires-Python: >=3.6
Requires-Dist: parse (>=1.19)
Requires-Dist: sqlparse (>=0.2.2)
